shoulder/__init__.py
shoulder/arthroplasty.py
shoulder/base.py
shoulder/bone.py
shoulder/glenoid/__init__.py
shoulder/humerus/__init__.py
shoulder/humerus/anatomic_neck.py
shoulder/humerus/angles.py
shoulder/humerus/bicipital_groove.py
shoulder/humerus/bone_props.py
shoulder/humerus/canal.py
shoulder/humerus/epicondyle.py
shoulder/humerus/mesh.py
shoulder/humerus/models/Unet_CRF_fil9.onnx
shoulder/humerus/models/rfc_bg3.onnx
shoulder/humerus/models/unetcrf_anp.onnx
shoulder/humerus/slice.py
shoulder/humerus/surgical_neck.py
shoulder/plotting.py
shoulder/utils.py
shoulder-1.5.0.dist-info/LICENSE.md
shoulder-1.5.0.dist-info/METADATA
shoulder-1.5.0.dist-info/WHEEL
shoulder-1.5.0.dist-info/RECORD
