Metadata-Version: 2.3
Name: shoulder
Version: 1.5.0
Summary: patient specific anatomic coordinate system generation for shoulder bones
License: MIT
Author: Gregory W Spangenberg
Author-email: gspangen@westerneng.ca
Requires-Python: >=3.10,<3.13
Classifier: License :: OSI Approved :: MIT License
Classifier: Programming Language :: Python :: 3
Classifier: Programming Language :: Python :: 3.10
Classifier: Programming Language :: Python :: 3.11
Classifier: Programming Language :: Python :: 3.12
Requires-Dist: circle-fit (>=0.1.3,<0.2.0)
Requires-Dist: lsq-ellipse (>=2.2.1,<3.0.0)
Requires-Dist: networkx (>=2.8.6)
Requires-Dist: onnxruntime (>=1.15.0,<2.0.0)
Requires-Dist: plotly (>=5.10.0)
Requires-Dist: rtree (>=1.0.0,<2.0.0)
Requires-Dist: ruptures (>=1.1.7,<2.0.0)
Requires-Dist: scikit-learn (>=1.2.2,<2.0.0)
Requires-Dist: scikit-spatial (>=6.5.0)
Requires-Dist: scipy (>=1.9.1,<2.0.0)
Requires-Dist: shapely (>=2.0,<3.0)
Requires-Dist: trimesh (>=4.0.0)
Project-URL: Repository, https://github.com/gregspangenberg/shoulder
